minecraftcrafting.py
pytp_recipescraper-0.0.2.dist-info/licenses/LICENSE.txt
pytp_recipescraper-0.0.2.dist-info/METADATA
pytp_recipescraper-0.0.2.dist-info/WHEEL
pytp_recipescraper-0.0.2.dist-info/top_level.txt
pytp_recipescraper-0.0.2.dist-info/RECORD
